binooculars-0.0.2.dist-info/METADATA
binooculars-0.0.2.dist-info/WHEEL
binooculars/cluster/__init__.py
binooculars/cluster/cluster.py
binooculars/linear/linear.py
binooculars/linear/__init__.py
binooculars/__init__.py
binooculars/binooculars.cpython-311-darwin.so
binooculars-0.0.2.dist-info/RECORD
