Metadata-Version: 2.1
Name: binooculars
Version: 0.0.2
Classifier: Programming Language :: Rust
Classifier: Programming Language :: Python :: Implementation :: CPython
Classifier: Programming Language :: Python :: Implementation :: PyPy
Summary: A tiny, yet blazingly fast machine learning library written in Rust with Python interface.
Author: Benedek Harsanyi
Requires-Python: >=3.7
